{"players":[{"name":"Colly","console":"fa-xbox","country":"gb","r1":"","r2":"","r3":"","r4":""},{"name":"Tenbobnote","console":"fa-playstation","country":"gb","r1":"","r2":"","r3":"","r4":""},{"name":"Kalessin","console":"fa-playstation","country":"gb","r1":"","r2":"","r3":"","r4":""},{"name":"Horusphoenix","console":"fa-xbox","country":"jp","r1":"","r2":"","r3":"","r4":""},{"name":"Hopz","console":"fa-playstation","country":"us","r1":"","r2":"","r3":"","r4":""},{"name":"Wing","console":"fa-playstation","country":"us","r1":"","r2":"","r3":"","r4":""},{"name":"Mr Longpole","console":"fa-xbox","country":"gb","r1":"","r2":"","r3":"","r4":""},{"name":"3offthetee","console":"fa-xbox","country":"gb","r1":"","r2":"","r3":"","r4":""},{"name":"Polekatt","console":"fa-steam","country":"us","r1":"","r2":"","r3":"","r4":""},{"name":"Geordieboy","console":"fa-playstation","country":"gb","r1":"","r2":"","r3":"","r4":""},{"name":"Hammersman","console":"fa-steam","country":"gb","r1":"","r2":"","r3":"","r4":""},{"name":"Dubz","console":"fa-playstation","country":"za","r1":"","r2":"","r3":"","r4":""},{"name":"Koof","console":"fa-steam","country":"us","r1":"","r2":"","r3":"","r4":""},{"name":"SimChars","console":"fa-playstation","country":"gb","r1":"","r2":"","r3":"","r4":""},{"name":"Arfabubble","console":"fa-playstation","country":"gb","r1":"","r2":"","r3":"","r4":""},{"name":"Bfctino","console":"fa-playstation","country":"gb","r1":"","r2":"","r3":"","r4":""}],"seasonEarnings":{"3offthetee":841091,"Colly":1501691,"Wing":1044666,"Kalessin":1164891,"Tenbobnote":629837,"Geordieboy":694191,"Dubz":183100,"Arfabubble":63900,"Hammersman":666309,"Mr Longpole":564162,"Bfctino":55600,"Hopz":293937,"Polekatt":558691,"Koof":201407,"SimChars":81982,"Horusphoenix":99055},"seasonPoints":{"3offthetee":1423,"Colly":3100,"Wing":1607,"Kalessin":1653,"Tenbobnote":1468,"Geordieboy":937,"Dubz":368,"Arfabubble":180,"Hammersman":984,"Mr Longpole":1063,"Bfctino":143,"Hopz":496,"Polekatt":633,"Koof":313,"SimChars":155,"Horusphoenix":135},"seasonEvents":{"3offthetee":8,"Colly":9,"Wing":7,"Kalessin":8,"Tenbobnote":7,"Geordieboy":8,"Dubz":4,"Arfabubble":2,"Hammersman":6,"Mr Longpole":7,"Bfctino":2,"Hopz":6,"Polekatt":8,"Koof":3,"SimChars":2,"Horusphoenix":1},"tourneyCount":null}